brightsites_sdk/__init__.py
brightsites_sdk/client.py
brightsites_sdk/models.py
brightsites_sdk/py.typed
idi_brightsites_sdk-0.2.0.dist-info/WHEEL
idi_brightsites_sdk-0.2.0.dist-info/METADATA
idi_brightsites_sdk-0.2.0.dist-info/RECORD
